amylodeep/__init__.py
amylodeep/cli.py
amylodeep/ensemble_predictor.py
amylodeep/esm_classifier.py
amylodeep/model_downloaded.py
amylodeep/unirep_model.py
amylodeep/utils.py
amylodeep-0.2.9.dist-info/licenses/LICENSE
amylodeep-0.2.9.dist-info/METADATA
amylodeep-0.2.9.dist-info/WHEEL
amylodeep-0.2.9.dist-info/entry_points.txt
amylodeep-0.2.9.dist-info/top_level.txt
amylodeep-0.2.9.dist-info/RECORD
