Metadata-Version: 2.4
Name: amylodeep
Version: 0.2.9
Summary: AmyloDeep: pLM-based ensemble model for predicting amyloid propensity from the amino acid sequence
Author-email: Alisa Davtyan <alisadavtyan7@gmail.com>
License: MIT
Project-URL: Repository, https://github.com/AlisaDavtyan/protein_classification
Project-URL: Bug Tracker, https://github.com/AlisaDavtyan/protein_classification/issues
Keywords: bioinformatics,amyloid,deep learning,protein,sequence classification
Classifier: Development Status :: 3 - Alpha
Classifier: Intended Audience :: Science/Research
Classifier: Topic :: Scientific/Engineering :: Bio-Informatics
Classifier: License :: OSI Approved :: MIT License
Classifier: Programming Language :: Python :: 3
Classifier: Programming Language :: Python :: 3.8
Classifier: Programming Language :: Python :: 3.9
Classifier: Programming Language :: Python :: 3.10
Classifier: Programming Language :: Python :: 3.11
Requires-Python: >=3.8
License-File: LICENSE
Requires-Dist: torch>=1.12.0
Requires-Dist: transformers>=4.30.0
Requires-Dist: huggingface_hub>=0.14.0
Requires-Dist: xgboost>=1.7.0
Requires-Dist: numpy>=1.20
Requires-Dist: pandas>=1.3
Requires-Dist: scikit-learn>=1.0
Requires-Dist: jax-unirep>=2.0.0
Provides-Extra: ui
Requires-Dist: matplotlib>=3.5; extra == "ui"
Provides-Extra: dev
Requires-Dist: black>=22.0; extra == "dev"
Requires-Dist: flake8>=3.9; extra == "dev"
Dynamic: license-file
